[
  {
    "timestamp": 1751196979.826829,
    "robot_id": "robot_2",
    "metric_type": "position",
    "value": [
      -2.1807281168600996,
      1.2393546474624542,
      0.0
    ],
    "metadata": {
      "orientation": 2.7874846249061624
    }
  },
  {
    "timestamp": 1751196979.8268318,
    "robot_id": "robot_3",
    "metric_type": "position",
    "value": [
      -6.290943536624249,
      1.89506706969141,
      0.0
    ],
    "metadata": {
      "orientation": 2.0721925898692106
    }
  },
  {
    "timestamp": 1751196979.8269088,
    "robot_id": "system",
    "metric_type": "performance",
    "value": {
      "avg_formation_error": 1.0825979550674527,
      "avg_control_effort": 1.5433595884426066,
      "avg_solve_time": 0.0,
      "max_solve_time": 0.0,
      "total_collisions": 0,
      "runtime": 269.01091480255127
    }
  },
  {
    "timestamp": 1751196979.826913,
    "robot_id": "vision_system",
    "metric_type": "vision_performance",
    "value": {
      "accuracy": 200.0,
      "detection_count": 50,
      "false_positives": 0,
      "missed_detections": 0,
      "detection_rate": 0.009338812103100485,
      "processing_time": 0.003908634185791016,
      "frame_count": 5354
    }
  },
  {
    "timestamp": 1751196981.8276439,
    "robot_id": "robot_0",
    "metric_type": "position",
    "value": [
      -2.3789586158057103,
      2.872962461504003,
      0.0
    ],
    "metadata": {
      "orientation": 2.988695074816474
    }
  },
  {
    "timestamp": 1751196981.8276548,
    "robot_id": "robot_1",
    "metric_type": "position",
    "value": [
      -4.0861566125946664,
      2.81254432244044,
      0.0
    ],
    "metadata": {
      "orientation": 2.975076319504578
    }
  },
  {
    "timestamp": 1751196981.827657,
    "robot_id": "robot_2",
    "metric_type": "position",
    "value": [
      -3.1867822433377992,
      2.3714370798599105,
      0.0
    ],
    "metadata": {
      "orientation": 2.9666929718217765
    }
  },
  {
    "timestamp": 1751196981.82766,
    "robot_id": "robot_3",
    "metric_type": "position",
    "value": [
      -8.050793340268866,
      2.765089558365996,
      0.0
    ],
    "metadata": {
      "orientation": 2.7942147140358844
    }
  },
  {
    "timestamp": 1751196981.827724,
    "robot_id": "system",
    "metric_type": "performance",
    "value": {
      "avg_formation_error": 1.1483540365095322,
      "avg_control_effort": 1.248361759555212,
      "avg_solve_time": 0.0,
      "max_solve_time": 0.0,
      "total_collisions": 0,
      "runtime": 271.0117299556732
    }
  },
  {
    "timestamp": 1751196981.827727,
    "robot_id": "vision_system",
    "metric_type": "vision_performance",
    "value": {
      "accuracy": 200.0,
      "detection_count": 50,
      "false_positives": 0,
      "missed_detections": 0,
      "detection_rate": 0.009269558769002595,
      "processing_time": 0.003203153610229492,
      "frame_count": 5394
    }
  },
  {
    "timestamp": 1751196983.8247418,
    "robot_id": "robot_0",
    "metric_type": "position",
    "value": [
      -4.021867033788317,
      2.7489907372535667,
      0.0
    ],
    "metadata": {
      "orientation": -2.7824295099497918
    }
  },
  {
    "timestamp": 1751196983.824759,
    "robot_id": "robot_1",
    "metric_type": "position",
    "value": [
      -5.784982164007191,
      3.27561532291376,
      0.0
    ],
    "metadata": {
      "orientation": -2.1360885837636765
    }
  },
  {
    "timestamp": 1751196983.824762,
    "robot_id": "robot_2",
    "metric_type": "position",
    "value": [
      -4.880623803619317,
      3.257360056231587,
      0.0
    ],
    "metadata": {
      "orientation": -3.0431501075799763
    }
  },
  {
    "timestamp": 1751196983.824764,
    "robot_id": "robot_3",
    "metric_type": "position",
    "value": [
      -9.756634335196495,
      2.8652028701962893,
      0.0
    ],
    "metadata": {
      "orientation": -2.7933892519012966
    }
  },
  {
    "timestamp": 1751196983.8248441,
    "robot_id": "system",
    "metric_type": "performance",
    "value": {
      "avg_formation_error": 1.2396556358898916,
      "avg_control_effort": 1.1861566884861525,
      "avg_solve_time": 0.0,
      "max_solve_time": 0.0,
      "total_collisions": 0,
      "runtime": 273.00884985923767
    }
  },
  {
    "timestamp": 1751196983.824848,
    "robot_id": "vision_system",
    "metric_type": "vision_performance",
    "value": {
      "accuracy": 200.0,
      "detection_count": 50,
      "false_positives": 0,
      "missed_detections": 0,
      "detection_rate": 0.009201324990798674,
      "processing_time": 0.003432035446166992,
      "frame_count": 5434
    }
  },
  {
    "timestamp": 1751196985.827992,
    "robot_id": "robot_0",
    "metric_type": "position",
    "value": [
      -4.67289138440654,
      2.5706864420233453,
      0.0
    ],
    "metadata": {
      "orientation": -2.2930652210867466
    }
  },
  {
    "timestamp": 1751196985.8280058,
    "robot_id": "robot_1",
    "metric_type": "position",
    "value": [
      -6.7706162987818335,
      3.7572135811675307,
      0.0
    ],
    "metadata": {
      "orientation": -1.5578441460965986
    }
  },
  {
    "timestamp": 1751196985.828009,
    "robot_id": "robot_2",
    "metric_type": "position",
    "value": [
      -5.937050545234652,
      4.20506180690003,
      0.0
    ],
    "metadata": {
      "orientation": -2.6621843374201326
    }
  },
  {
    "timestamp": 1751196985.828011,
    "robot_id": "robot_3",
    "metric_type": "position",
    "value": [
      -10.677189331575132,
      2.651761624640649,
      0.0
    ],
    "metadata": {
      "orientation": -2.393153222088588
    }
  },
  {
    "timestamp": 1751196985.828086,
    "robot_id": "system",
    "metric_type": "performance",
    "value": {
      "avg_formation_error": 1.3589412813610255,
      "avg_control_effort": 1.0504744341020908,
      "avg_solve_time": 0.0,
      "max_solve_time": 0.0,
      "total_collisions": 0,
      "runtime": 275.0120918750763
    }
  },
  {
    "timestamp": 1751196985.8280902,
    "robot_id": "vision_system",
    "metric_type": "vision_performance",
    "value": {
      "accuracy": 200.0,
      "detection_count": 51,
      "false_positives": 0,
      "missed_detections": 0,
      "detection_rate": 0.009316770186335404,
      "processing_time": 0.004079103469848633,
      "frame_count": 5474
    }
  },
  {
    "timestamp": 1751196987.82732,
    "robot_id": "robot_0",
    "metric_type": "position",
    "value": [
      -4.966122172430482,
      1.8299358360492564,
      0.0
    ],
    "metadata": {
      "orientation": -1.9945360346858179
    }
  },
  {
    "timestamp": 1751196987.827335,
    "robot_id": "robot_1",
    "metric_type": "position",
    "value": [
      -6.021659194584365,
      3.5132507822983654,
      0.0
    ],
    "metadata": {
      "orientation": -1.9108502449768487
    }
  },
  {
    "timestamp": 1751196987.827337,
    "robot_id": "robot_2",
    "metric_type": "position",
    "value": [
      -6.040043522185569,
      4.640384439072343,
      0.0
    ],
    "metadata": {
      "orientation": -2.367008658867024
    }
  },
  {
    "timestamp": 1751196987.827338,
    "robot_id": "robot_3",
    "metric_type": "position",
    "value": [
      -10.788691409644063,
      1.9218919117053865,
      0.0
    ],
    "metadata": {
      "orientation": -2.435854406988569
    }
  },
  {
    "timestamp": 1751196987.827414,
    "robot_id": "system",
    "metric_type": "performance",
    "value": {
      "avg_formation_error": 1.546433483577443,
      "avg_control_effort": 1.2194547293504872,
      "avg_solve_time": 0.0,
      "max_solve_time": 0.0,
      "total_collisions": 0,
      "runtime": 277.0114209651947
    }
  },
  {
    "timestamp": 1751196987.8274171,
    "robot_id": "vision_system",
    "metric_type": "vision_performance",
    "value": {
      "accuracy": 200.0,
      "detection_count": 51,
      "false_positives": 0,
      "missed_detections": 0,
      "detection_rate": 0.009249183895538629,
      "processing_time": 0.003094911575317383,
      "frame_count": 5514
    }
  },
  {
    "timestamp": 1751196989.829709,
    "robot_id": "robot_0",
    "metric_type": "position",
    "value": [
      -6.226785363980107,
      0.6798256956162719,
      0.0
    ],
    "metadata": {
      "orientation": -1.565437237199611
    }
  },
  {
    "timestamp": 1751196989.829721,
    "robot_id": "robot_1",
    "metric_type": "position",
    "value": [
      -6.581022414200639,
      1.9907828263856804,
      0.0
    ],
    "metadata": {
      "orientation": -2.5013831579554187
    }
  },
  {
    "timestamp": 1751196989.8297238,
    "robot_id": "robot_2",
    "metric_type": "position",
    "value": [
      -6.038808435010144,
      3.8257657766385775,
      0.0
    ],
    "metadata": {
      "orientation": -2.491098484645772
    }
  },
  {
    "timestamp": 1751196989.829726,
    "robot_id": "robot_3",
    "metric_type": "position",
    "value": [
      -12.06083348681735,
      0.967402834481416,
      0.0
    ],
    "metadata": {
      "orientation": -2.2007157731016993
    }
  },
  {
    "timestamp": 1751196989.829802,
    "robot_id": "system",
    "metric_type": "performance",
    "value": {
      "avg_formation_error": 1.946470397031643,
      "avg_control_effort": 1.175157696747822,
      "avg_solve_time": 0.0,
      "max_solve_time": 0.0,
      "total_collisions": 0,
      "runtime": 279.0138077735901
    }
  },
  {
    "timestamp": 1751196989.829806,
    "robot_id": "vision_system",
    "metric_type": "vision_performance",
    "value": {
      "accuracy": 200.0,
      "detection_count": 51,
      "false_positives": 0,
      "missed_detections": 0,
      "detection_rate": 0.009182571119913576,
      "processing_time": 0.003812074661254883,
      "frame_count": 5554
    }
  },
  {
    "timestamp": 1751196991.830543,
    "robot_id": "robot_0",
    "metric_type": "position",
    "value": [
      -6.426735953218238,
      -1.1679378975323196,
      0.0
    ],
    "metadata": {
      "orientation": -1.1954854605516354
    }
  },
  {
    "timestamp": 1751196991.8305569,
    "robot_id": "robot_1",
    "metric_type": "position",
    "value": [
      -7.8431812429132,
      0.4717229333518425,
      0.0
    ],
    "metadata": {
      "orientation": -1.9688936172629696
    }
  },
  {
    "timestamp": 1751196991.83056,
    "robot_id": "robot_2",
    "metric_type": "position",
    "value": [
      -7.357963591127411,
      2.4467275892684492,
      0.0
    ],
    "metadata": {
      "orientation": -2.301200714096068
    }
  },
  {
    "timestamp": 1751196991.830563,
    "robot_id": "robot_3",
    "metric_type": "position",
    "value": [
      -12.494820135257857,
      -0.8837772705541979,
      0.0
    ],
    "metadata": {
      "orientation": -1.4154267822613942
    }
  },
  {
    "timestamp": 1751196991.83064,
    "robot_id": "system",
    "metric_type": "performance",
    "value": {
      "avg_formation_error": 2.321758657095294,
      "avg_control_effort": 1.1097753695871655,
      "avg_solve_time": 0.0,
      "max_solve_time": 0.0,
      "total_collisions": 0,
      "runtime": 281.0146460533142
    }
  },
  {
    "timestamp": 1751196991.830644,
    "robot_id": "vision_system",
    "metric_type": "vision_performance",
    "value": {
      "accuracy": 200.0,
      "detection_count": 51,
      "false_positives": 0,
      "missed_detections": 0,
      "detection_rate": 0.009116910976045764,
      "processing_time": 0.004027843475341797,
      "frame_count": 5594
    }
  },
  {
    "timestamp": 1751196993.8283179,
    "robot_id": "robot_0",
    "metric_type": "position",
    "value": [
      -5.885128115727513,
      -1.624761657205525,
      0.0
    ],
    "metadata": {
      "orientation": -0.9757394686495411
    }
  },
  {
    "timestamp": 1751196993.8283331,
    "robot_id": "robot_1",
    "metric_type": "position",
    "value": [
      -8.065575678710633,
      -1.4383340153259658,
      0.0
    ],
    "metadata": {
      "orientation": -1.0964230221185922
    }
  },
  {
    "timestamp": 1751196993.8283362,
    "robot_id": "robot_2",
    "metric_type": "position",
    "value": [
      -8.536753112608192,
      0.8348065468315046,
      0.0
    ],
    "metadata": {
      "orientation": -2.0987383444766325
    }
  },
  {
    "timestamp": 1751196993.828338,
    "robot_id": "robot_3",
    "metric_type": "position",
    "value": [
      -12.012226988732786,
      -1.5971661437860674,
      0.0
    ],
    "metadata": {
      "orientation": -0.2689811020008907
    }
  },
  {
    "timestamp": 1751196993.828414,
    "robot_id": "system",
    "metric_type": "performance",
    "value": {
      "avg_formation_error": 2.151991885458261,
      "avg_control_effort": 1.003867006670568,
      "avg_solve_time": 0.0,
      "max_solve_time": 0.0,
      "total_collisions": 0,
      "runtime": 283.01241993904114
    }
  },
  {
    "timestamp": 1751196993.828418,
    "robot_id": "vision_system",
    "metric_type": "vision_performance",
    "value": {
      "accuracy": 200.0,
      "detection_count": 51,
      "false_positives": 0,
      "missed_detections": 0,
      "detection_rate": 0.009052183173588925,
      "processing_time": 0.0033516883850097656,
      "frame_count": 5634
    }
  },
  {
    "timestamp": 1751196995.827245,
    "robot_id": "robot_0",
    "metric_type": "position",
    "value": [
      -4.2942132286236925,
      -2.49938917664779,
      0.0
    ],
    "metadata": {
      "orientation": -0.8248488948990214
    }
  },
  {
    "timestamp": 1751196995.82726,
    "robot_id": "robot_1",
    "metric_type": "position",
    "value": [
      -7.219296750072862,
      -1.7588580530600701,
      0.0
    ],
    "metadata": {
      "orientation": -0.6421955688941583
    }
  },
  {
    "timestamp": 1751196995.8272629,
    "robot_id": "robot_2",
    "metric_type": "position",
    "value": [
      -8.986475369215373,
      -1.0520708835425172,
      0.0
    ],
    "metadata": {
      "orientation": -1.2546159939459407
    }
  },
  {
    "timestamp": 1751196995.827265,
    "robot_id": "robot_3",
    "metric_type": "position",
    "value": [
      -10.746742453735003,
      -2.165549484311239,
      0.0
    ],
    "metadata": {
      "orientation": -0.6000394918182879
    }
  },
  {
    "timestamp": 1751196995.827344,
    "robot_id": "system",
    "metric_type": "performance",
    "value": {
      "avg_formation_error": 1.4950769999532936,
      "avg_control_effort": 0.995675509421873,
      "avg_solve_time": 0.0,
      "max_solve_time": 0.0,
      "total_collisions": 0,
      "runtime": 285.01134991645813
    }
  },
  {
    "timestamp": 1751196995.827349,
    "robot_id": "vision_system",
    "metric_type": "vision_performance",
    "value": {
      "accuracy": 200.0,
      "detection_count": 51,
      "false_positives": 0,
      "missed_detections": 0,
      "detection_rate": 0.008988367994360239,
      "processing_time": 0.0034601688385009766,
      "frame_count": 5674
    }
  },
  {
    "timestamp": 1751196997.824546,
    "robot_id": "robot_0",
    "metric_type": "position",
    "value": [
      -3.3890681762014787,
      -4.1194834032889664,
      0.0
    ],
    "metadata": {
      "orientation": -0.5217967552802223
    }
  },
  {
    "timestamp": 1751196997.8245592,
    "robot_id": "robot_1",
    "metric_type": "position",
    "value": [
      -7.054681232381416,
      -1.743504465714553,
      0.0
    ],
    "metadata": {
      "orientation": -0.9665297551731475
    }
  },
  {
    "timestamp": 1751196997.8245609,
    "robot_id": "robot_2",
    "metric_type": "position",
    "value": [
      -8.12708085729336,
      -2.6640794711789155,
      0.0
    ],
    "metadata": {
      "orientation": -1.1334524550406082
    }
  },
  {
    "timestamp": 1751196997.8245618,
    "robot_id": "robot_3",
    "metric_type": "position",
    "value": [
      -9.67997432808688,
      -3.6821474099713276,
      0.0
    ],
    "metadata": {
      "orientation": -1.190255020501747
    }
  },
  {
    "timestamp": 1751196997.8246248,
    "robot_id": "system",
    "metric_type": "performance",
    "value": {
      "avg_formation_error": 1.1971170576496966,
      "avg_control_effort": 1.1026664043761498,
      "avg_solve_time": 0.0,
      "max_solve_time": 0.0,
      "total_collisions": 0,
      "runtime": 287.00863099098206
    }
  },
  {
    "timestamp": 1751196997.8246279,
    "robot_id": "vision_system",
    "metric_type": "vision_performance",
    "value": {
      "accuracy": 200.0,
      "detection_count": 52,
      "false_positives": 0,
      "missed_detections": 0,
      "detection_rate": 0.009100455022751138,
      "processing_time": 0.002990245819091797,
      "frame_count": 5714
    }
  },
  {
    "timestamp": 1751196999.829589,
    "robot_id": "robot_0",
    "metric_type": "position",
    "value": [
      -1.581603883371247,
      -4.862333236094013,
      0.0
    ],
    "metadata": {
      "orientation": -0.21907479193882298
    }
  },
  {
    "timestamp": 1751196999.829603,
    "robot_id": "robot_1",
    "metric_type": "position",
    "value": [
      -7.029450366699754,
      -1.61485422409299,
      0.0
    ],
    "metadata": {
      "orientation": -0.7577045179638754
    }
  },
  {
    "timestamp": 1751196999.8296058,
    "robot_id": "robot_2",
    "metric_type": "position",
    "value": [
      -8.21382442378268,
      -2.79216722692448,
      0.0
    ],
    "metadata": {
      "orientation": -0.6965839437275081
    }
  },
  {
    "timestamp": 1751196999.829609,
    "robot_id": "robot_3",
    "metric_type": "position",
    "value": [
      -8.682099878293934,
      -4.653139543861,
      0.0
    ],
    "metadata": {
      "orientation": -0.2134008535782575
    }
  },
  {
    "timestamp": 1751196999.829685,
    "robot_id": "system",
    "metric_type": "performance",
    "value": {
      "avg_formation_error": 1.7104935092767997,
      "avg_control_effort": 1.1799152452562918,
      "avg_solve_time": 0.0,
      "max_solve_time": 0.0,
      "total_collisions": 0,
      "runtime": 289.0136909484863
    }
  },
  {
    "timestamp": 1751196999.829689,
    "robot_id": "vision_system",
    "metric_type": "vision_performance",
    "value": {
      "accuracy": 200.0,
      "detection_count": 52,
      "false_positives": 0,
      "missed_detections": 0,
      "detection_rate": 0.009037191518943343,
      "processing_time": 0.003695249557495117,
      "frame_count": 5754
    }
  },
  {
    "timestamp": 1751197001.8245199,
    "robot_id": "robot_0",
    "metric_type": "position",
    "value": [
      -0.5822821857449066,
      -5.612219208901867,
      0.0
    ],
    "metadata": {
      "orientation": 0.11830245107782336
    }
  },
  {
    "timestamp": 1751197001.8245351,
    "robot_id": "robot_1",
    "metric_type": "position",
    "value": [
      -6.473907401517442,
      -1.1044752381751448,
      0.0
    ],
    "metadata": {
      "orientation": -0.8456991311526458
    }
  },
  {
    "timestamp": 1751197001.8245382,
    "robot_id": "robot_2",
    "metric_type": "position",
    "value": [
      -7.903573048908848,
      -3.7386661932159977,
      0.0
    ],
    "metadata": {
      "orientation": -0.5311416224877222
    }
  },
  {
    "timestamp": 1751197001.82454,
    "robot_id": "robot_3",
    "metric_type": "position",
    "value": [
      -6.966663547722388,
      -5.339049507787446,
      0.0
    ],
    "metadata": {
      "orientation": -0.5395897105693926
    }
  },
  {
    "timestamp": 1751197001.824605,
    "robot_id": "system",
    "metric_type": "performance",
    "value": {
      "avg_formation_error": 2.604829877461525,
      "avg_control_effort": 1.1435105265000547,
      "avg_solve_time": 0.0,
      "max_solve_time": 0.0,
      "total_collisions": 0,
      "runtime": 291.00861072540283
    }
  },
  {
    "timestamp": 1751197001.824609,
    "robot_id": "vision_system",
    "metric_type": "vision_performance",
    "value": {
      "accuracy": 200.0,
      "detection_count": 52,
      "false_positives": 0,
      "missed_detections": 0,
      "detection_rate": 0.008974801518812565,
      "processing_time": 0.003191232681274414,
      "frame_count": 5794
    }
  },
  {
    "timestamp": 1751197003.827761,
    "robot_id": "robot_0",
    "metric_type": "position",
    "value": [
      0.6501966151866441,
      -6.302008400642545,
      0.0
    ],
    "metadata": {
      "orientation": 0.4751488618886834
    }
  },
  {
    "timestamp": 1751197003.827779,
    "robot_id": "robot_1",
    "metric_type": "position",
    "value": [
      -6.436761298977519,
      -1.0774292671327295,
      0.0
    ],
    "metadata": {
      "orientation": -0.8109758908523852
    }
  },
  {
    "timestamp": 1751197003.827782,
    "robot_id": "robot_2",
    "metric_type": "position",
    "value": [
      -6.646499391160988,
      -5.107617284579906,
      0.0
    ],
    "metadata": {
      "orientation": -0.36628610715791277
    }
  },
  {
    "timestamp": 1751197003.8277838,
    "robot_id": "robot_3",
    "metric_type": "position",
    "value": [
      -5.611637200597891,
      -6.224653287529256,
      0.0
    ],
    "metadata": {
      "orientation": -0.35701290895581145
    }
  },
  {
    "timestamp": 1751197003.827859,
    "robot_id": "system",
    "metric_type": "performance",
    "value": {
      "avg_formation_error": 3.2938685195030963,
      "avg_control_effort": 0.9787534599937728,
      "avg_solve_time": 0.0,
      "max_solve_time": 0.0,
      "total_collisions": 0,
      "runtime": 293.011864900589
    }
  },
  {
    "timestamp": 1751197003.827863,
    "robot_id": "vision_system",
    "metric_type": "vision_performance",
    "value": {
      "accuracy": 200.0,
      "detection_count": 52,
      "false_positives": 0,
      "missed_detections": 0,
      "detection_rate": 0.008913267055193692,
      "processing_time": 0.0038957595825195312,
      "frame_count": 5834
    }
  },
  {
    "timestamp": 1751197005.830105,
    "robot_id": "robot_0",
    "metric_type": "position",
    "value": [
      2.4306649036954413,
      -6.177139372134887,
      0.0
    ],
    "metadata": {
      "orientation": 0.8063407470631923
    }
  },
  {
    "timestamp": 1751197005.830122,
    "robot_id": "robot_1",
    "metric_type": "position",
    "value": [
      -6.086300715664059,
      -1.255036624049333,
      0.0
    ],
    "metadata": {
      "orientation": -0.6633863162088984
    }
  },
  {
    "timestamp": 1751197005.830125,
    "robot_id": "robot_2",
    "metric_type": "position",
    "value": [
      -4.755660709884679,
      -5.6987456065792115,
      0.0
    ],
    "metadata": {
      "orientation": -0.17882015729320339
    }
  },
  {
    "timestamp": 1751197005.8301282,
    "robot_id": "robot_3",
    "metric_type": "position",
    "value": [
      -3.8660781517252905,
      -6.316813822551629,
      0.0
    ],
    "metadata": {
      "orientation": 0.32177742738903564
    }
  },
  {
    "timestamp": 1751197005.830217,
    "robot_id": "system",
    "metric_type": "performance",
    "value": {
      "avg_formation_error": 3.620642173569109,
      "avg_control_effort": 0.9589074338599671,
      "avg_solve_time": 0.0,
      "max_solve_time": 0.0,
      "total_collisions": 0,
      "runtime": 295.0142228603363
    }
  },
  {
    "timestamp": 1751197005.8302221,
    "robot_id": "vision_system",
    "metric_type": "vision_performance",
    "value": {
      "accuracy": 200.0,
      "detection_count": 52,
      "false_positives": 0,
      "missed_detections": 0,
      "detection_rate": 0.008852570650323459,
      "processing_time": 0.0037910938262939453,
      "frame_count": 5874
    }
  },
  {
    "timestamp": 1751197007.829121,
    "robot_id": "robot_0",
    "metric_type": "position",
    "value": [
      3.888915435469518,
      -4.8345136969826195,
      0.0
    ],
    "metadata": {
      "orientation": 1.081005024513004
    }
  },
  {
    "timestamp": 1751197007.829139,
    "robot_id": "robot_1",
    "metric_type": "position",
    "value": [
      -5.466355041627702,
      -1.4754991611675885,
      0.0
    ],
    "metadata": {
      "orientation": -0.4525190220242822
    }
  },
  {
    "timestamp": 1751197007.829142,
    "robot_id": "robot_2",
    "metric_type": "position",
    "value": [
      -3.023274112420386,
      -5.681750954541929,
      0.0
    ],
    "metadata": {
      "orientation": 0.22988318502359276
    }
  },
  {
    "timestamp": 1751197007.829144,
    "robot_id": "robot_3",
    "metric_type": "position",
    "value": [
      -2.2259576295899475,
      -5.114498944140389,
      0.0
    ],
    "metadata": {
      "orientation": 1.1089070379403565
    }
  },
  {
    "timestamp": 1751197007.829222,
    "robot_id": "system",
    "metric_type": "performance",
    "value": {
      "avg_formation_error": 3.810140310092274,
      "avg_control_effort": 0.9748359099682133,
      "avg_solve_time": 0.0,
      "max_solve_time": 0.0,
      "total_collisions": 0,
      "runtime": 297.0132279396057
    }
  },
  {
    "timestamp": 1751197007.829226,
    "robot_id": "vision_system",
    "metric_type": "vision_performance",
    "value": {
      "accuracy": 200.0,
      "detection_count": 52,
      "false_positives": 0,
      "missed_detections": 0,
      "detection_rate": 0.00879269529928982,
      "processing_time": 0.003963947296142578,
      "frame_count": 5914
    }
  },
  {
    "timestamp": 1751197009.824496,
    "robot_id": "robot_0",
    "metric_type": "position",
    "value": [
      4.626528921998292,
      -2.9801371671843695,
      0.0
    ],
    "metadata": {
      "orientation": 1.3098722113735262
    }
  },
  {
    "timestamp": 1751197009.824511,
    "robot_id": "robot_1",
    "metric_type": "position",
    "value": [
      -3.4463754695845403,
      -2.6407994486927104,
      0.0
    ],
    "metadata": {
      "orientation": -0.10175885866903914
    }
  },
  {
    "timestamp": 1751197009.824513,
    "robot_id": "robot_2",
    "metric_type": "position",
    "value": [
      -1.4693501948962446,
      -4.890811016872428,
      0.0
    ],
    "metadata": {
      "orientation": 0.7076694886268557
    }
  },
  {
    "timestamp": 1751197009.824516,
    "robot_id": "robot_3",
    "metric_type": "position",
    "value": [
      -1.6645768600916988,
      -3.340310170252021,
      0.0
    ],
    "metadata": {
      "orientation": 0.9459704837929082
    }
  },
  {
    "timestamp": 1751197009.824576,
    "robot_id": "system",
    "metric_type": "performance",
    "value": {
      "avg_formation_error": 3.7174574985711164,
      "avg_control_effort": 1.013757802259459,
      "avg_solve_time": 0.0,
      "max_solve_time": 0.0,
      "total_collisions": 0,
      "runtime": 299.00858187675476
    }
  },
  {
    "timestamp": 1751197009.824579,
    "robot_id": "vision_system",
    "metric_type": "vision_performance",
    "value": {
      "accuracy": 200.0,
      "detection_count": 52,
      "false_positives": 0,
      "missed_detections": 0,
      "detection_rate": 0.008733624454148471,
      "processing_time": 0.0031249523162841797,
      "frame_count": 5954
    }
  },
  {
    "timestamp": 1751197011.829254,
    "robot_id": "robot_0",
    "metric_type": "position",
    "value": [
      4.908790963020574,
      -1.005330596133329,
      0.0
    ],
    "metadata": {
      "orientation": 1.55833356030851
    }
  },
  {
    "timestamp": 1751197011.829267,
    "robot_id": "robot_1",
    "metric_type": "position",
    "value": [
      -1.5118190506580669,
      -2.5166131810078585,
      0.0
    ],
    "metadata": {
      "orientation": 0.2878123010055386
    }
  },
  {
    "timestamp": 1751197011.8292701,
    "robot_id": "robot_2",
    "metric_type": "position",
    "value": [
      -1.5183436962473298,
      -3.673341794363296,
      0.0
    ],
    "metadata": {
      "orientation": 0.8358440397256349
    }
  },
  {
    "timestamp": 1751197011.829272,
    "robot_id": "robot_3",
    "metric_type": "position",
    "value": [
      -1.0740675802387516,
      -1.37480737551713,
      0.0
    ],
    "metadata": {
      "orientation": 1.540452685717277
    }
  },
  {
    "timestamp": 1751197011.829341,
    "robot_id": "system",
    "metric_type": "performance",
    "value": {
      "avg_formation_error": 3.3626316889550787,
      "avg_control_effort": 1.027977677912654,
      "avg_solve_time": 0.0,
      "max_solve_time": 0.0,
      "total_collisions": 0,
      "runtime": 301.0133469104767
    }
  },
  {
    "timestamp": 1751197011.829345,
    "robot_id": "vision_system",
    "metric_type": "vision_performance",
    "value": {
      "accuracy": 200.0,
      "detection_count": 52,
      "false_positives": 0,
      "missed_detections": 0,
      "detection_rate": 0.008675342008675343,
      "processing_time": 0.003573894500732422,
      "frame_count": 5994
    }
  }
]